mcpsse/__init__.py
mcpsse/__main__.py
mcpsse/server.py
mcp_sse-0.3.0.dist-info/METADATA
mcp_sse-0.3.0.dist-info/WHEEL
mcp_sse-0.3.0.dist-info/entry_points.txt
mcp_sse-0.3.0.dist-info/top_level.txt
mcp_sse-0.3.0.dist-info/RECORD
