Metadata-Version: 2.4
Name: mcp-sse
Version: 0.3.0
Summary: Add your description here
Requires-Python: >=3.12
Requires-Dist: build>=1.2.2.post1
Requires-Dist: httpx>=0.28.1
Requires-Dist: mcp>=1.6.0
Requires-Dist: twine>=6.1.0
